odoo8_addon_mass_mailing_sending_queue-8.0.1.0.0-py2.7-nspkg.pth
odoo8_addon_mass_mailing_sending_queue-8.0.1.0.0.dist-info/top_level.txt
odoo8_addon_mass_mailing_sending_queue-8.0.1.0.0.dist-info/WHEEL
odoo8_addon_mass_mailing_sending_queue-8.0.1.0.0.dist-info/RECORD
odoo8_addon_mass_mailing_sending_queue-8.0.1.0.0.dist-info/metadata.json
odoo8_addon_mass_mailing_sending_queue-8.0.1.0.0.dist-info/DESCRIPTION.rst
odoo8_addon_mass_mailing_sending_queue-8.0.1.0.0.dist-info/METADATA
odoo8_addon_mass_mailing_sending_queue-8.0.1.0.0.dist-info/namespace_packages.txt
odoo_addons/mass_mailing_sending_queue/__openerp__.py
odoo_addons/mass_mailing_sending_queue/__init__.py
odoo_addons/mass_mailing_sending_queue/README.rst
odoo_addons/mass_mailing_sending_queue/security/ir.model.access.csv
odoo_addons/mass_mailing_sending_queue/models/mail_mail.py
odoo_addons/mass_mailing_sending_queue/models/mail_mail_statistics.py
odoo_addons/mass_mailing_sending_queue/models/__init__.py
odoo_addons/mass_mailing_sending_queue/models/mail_mass_mailing_sending.py
odoo_addons/mass_mailing_sending_queue/models/mail_mass_mailing.py
odoo_addons/mass_mailing_sending_queue/i18n/es.po
odoo_addons/mass_mailing_sending_queue/views/mass_mailing_view.xml
odoo_addons/mass_mailing_sending_queue/views/mass_mailing_sending_view.xml
odoo_addons/mass_mailing_sending_queue/data/ir_config_parameter.xml
odoo_addons/mass_mailing_sending_queue/data/ir_cron.xml
odoo_addons/mass_mailing_sending_queue/tests/__init__.py
odoo_addons/mass_mailing_sending_queue/tests/test_mass_mailing_sending.py
odoo_addons/mass_mailing_sending_queue/static/description/icon.png
